elliptic_meshql/Computer.py
elliptic_meshql/Manager.py
elliptic_meshql/MapFunctions.py
elliptic_meshql/MeshQL.py
elliptic_meshql/ReduceFunctions.py
elliptic_meshql/Selector.py
elliptic_meshql/__init__.py
elliptic_meshql-0.2.5.dist-info/METADATA
elliptic_meshql-0.2.5.dist-info/RECORD
elliptic_meshql-0.2.5.dist-info/WHEEL
elliptic_meshql-0.2.5.dist-info/top_level.txt
