Metadata-Version: 2.1
Name: elliptic-meshql
Version: 0.2.5
Summary: ELLIPTIc DSL Contracts for MeshQL.
Home-page: https://github.com/padmec-reservoir/elliptic_meshql
Author: Guilherme Caminha
Author-email: gpkc@cin.ufpe.br
License: MIT license
Keywords: elliptic_meshql
Platform: UNKNOWN
Classifier: Development Status :: 2 - Pre-Alpha
Classifier: Intended Audience :: Developers
Classifier: License :: OSI Approved :: MIT License
Classifier: Natural Language :: English
Classifier: Programming Language :: Python :: 3
Classifier: Programming Language :: Python :: 3.6
Requires-Dist: elliptic
